MIPS Nios2 Processor Design/nios2.v
module nios2(instruction18, clk18);
  input clk18;
  input [31:0] instruction18;
  reg [31:0] out_dp18;
  reg [31:0] pc18,ir18,ALUout18,target18,pc18_inc,memory18,pc_wb18;
  reg [4:0] source_a18,source_b18,destination_18;
  reg [5:0] opcode18;
  reg [31:0] r0_18 ,r1_18,r4_18,r5_18,four18,one18,pc_loop18;
  reg [31:0] N_18;
  reg[31:0] r2_18[0:31],r6_18;
  reg[31:0] r3_18[0:31],r7_18;
  reg[31:0] r8_18;
  reg rtype18;
  reg jtype18;
  reg itype18;
  reg [7:0] r2_addr18,r3_addr18,r6_addr18,r7_addr18,r8_addr18;
  initial begin
    pc18 = 0;
    pc18_inc = 4;
    pc_loop18 = 8;// loop at pc=12 
    four18 = 4;
    one18 = 1;
    ir18 = 0;
    out_dp18 = 0;
    rtype18 = 0;
    jtype18 = 0;
    itype18 = 0;
    r0_18 = 0;
    r2_18[0] = 5;
    r2_18[4] = 3;
    r2_18[8] = -6;
    r2_18[12] = 19;
    r2_18[16] = 8;
    r2_18[20] = 12;
    r3_18[0] = 2;
    r3_18[4] = 14;
    r3_18[8] = -3;
    r3_18[12] = 2;
    r3_18[16] = -5;
    r3_18[20] = 36;
    N_18 = 6;  //no. of iterations
    r2_addr18 = 0;
    r3_addr18 = 0;
    r6_addr18 = 0;
    r7_addr18 = 0;
    r8_addr18 = 0;
    r4_18 = 1;
  end
  always @(instruction18) begin
    //fetch nf(instruction18, pc18, ir18,clk18);
    //decode nd(source_a18,source_b18,ir18,opcode18,clk18); 
    /**************** Fetch Stage*********************/ 
    ir18 = instruction18;
    pc18 = pc18 + pc18_inc;
    pc_wb18 = pc18;
    /*****************Decode Stage*********************/
    // checking the Op-code and identifying the instruction as i-type,
    // r-type and j-type 
    opcode18 = ir18[5:0];
    if (opcode18 == 6'b111010) begin
       rtype18 = 1;
       source_a18 = ir18[31:27];
       source_b18 = ir18[26:22];
       destination_18 = ir18[21:17];
     end else begin
       itype18 = 1;
       source_a18 = ir18[31:27];
       source_b18 = ir18[26:22];
       destination_18 = ir18[31:27];
     end
     /*********************Execute Stage********************/
    case(pc18)
      4: begin
        ALUout18 = N_18;         // Executing ldw r4,0(r4)
         end
      8: begin
          ALUout18 = r0_18 + r0_18;// Executing add r5,r0,r0
         end
      12: begin
           ALUout18 = r2_18[r2_addr18];// Executing ldw r6,0(r2)
          end
      16: begin
           ALUout18 = r3_18[r3_addr18];// Executing ldw r7,0(r3)
          end
      20: begin
           ALUout18 = r6_18 * r7_18;// Executing mul r8,r6,r7
           //r6_addr18 = r6_addr18 + four18;
           //r7_addr18 = r7_addr18 + four18;
          end
      24: begin
           ALUout18 = r5_18 + r8_18;// Executing add r5,r5,r8
           //r8_addr18 = r8_addr18 + four18;
          end
      28: begin
           ALUout18 = r2_addr18 + four18;// Executing addi r2,r2,4
          end
      32: begin
           ALUout18 = r3_addr18 + four18;// Executing addi r3,r3,4
          end
      36: begin
           ALUout18 = r4_18 - one18;// Executing subi r4,r4,1
          end
      40: begin
           ALUout18 = r4_18 - r0_18;
          end        
      44: begin
          if (ir18[15] == 1) begin// Executing stw r5,DOT_PRODUCT(r0)
            ALUout18 = r5_18 + {16'hFFFF,ir18[15:0]};
          end else begin
            ALUout18 = r5_18 + {16'h0000,ir18[15:0]};
          end
        end
      default: ;//do nothing
    endcase
    /*********************Memory Stage***********************/
    //Catagorising according to instruction type(R-type,Load,Store,Branch on equal,etc)
    if (opcode18 == 6'b010111) begin //load instructions
      memory18 = ALUout18;
    end
    else if (opcode18 == 6'b111010) begin //R-type instructions
      memory18 = ALUout18;
    end
    else if (opcode18 == 6'b010101) begin//store instructions
      memory18 = ALUout18;
    end
    else begin//I-type instructions
      memory18 = ALUout18;
    end
    /*********************WriteBack Stage********************/
    case(pc_wb18)
      4: begin
          r4_18 = memory18;         // WriteBack ldw r4,0(r4)
         end
      8: begin
          r5_18 = memory18;         // WriteBack add r5,r0,r0
         end
      12: begin
           r6_18 = memory18;// WriteBack ldw r6,0(r2)
           //r6_addr18 = r6_addr18 + four18;
        end
      16: begin
           r7_18 = memory18;// WriteBack ldw r7,0(r3)
           //r7_addr18 = r7_addr18 + four18;
          end
      20: begin
           r8_18 = memory18;// WriteBack mul r8,r6,r7
           //r8_addr18 = r8_addr18 + four18;
          end
      24: begin
           r5_18 = memory18;// WriteBack add r5,r5,r8
          end
      28: begin
           r2_addr18 = memory18;// WriteBack addi r2,r2,4
          end
      32: begin
           r3_addr18 = memory18;// WriteBack addi r3,r3,4
          end
      36: begin
           r4_18 = memory18;// WriteBack subi r4,r4,1
          end
      40: begin
           if (ALUout18 != 0) begin    // WriteBack bgt r4,r0,loop(pc18 = 12)
             pc18 = pc_loop18;
           end else begin
             pc18 = pc18;
           end
          end         
      44: begin
            r5_18 = memory18;
          end
      default: ;//do nothing
    endcase
  end
endmodule

MIPS Nios2 Processor Design/nio2_tb.v
`timescale 1ms/10us

`include "nios2.v"

module nios2_tb();
  wire [31:0] sum18;
  reg [31:0] instruction18;
  reg clk18;
  nios2 ft_tb(instruction18,clk18);
   
  initial begin
    clk18=0;
    repeat(50) begin
      #5 
      clk18 = ~clk18;
    end  
  end

  initial begin
    
    #5;
    
    instruction18 = 32'h21000017; //ldw r4,0(r4)
    #10;
    instruction18 = 32'h000A0C7A; //add r5,r0,r0
    #10;
    repeat(6) begin 
      instruction18 = 32'h118000173;//ldw r6,0(r4)(loop)
      #10;
      instruction18 = 32'h19C00017;//ldw r7,0(r3)
      #10;
      instruction18 = 32'h31D009FA;//mul r8,r6,r7
      #10;
      instruction18 = 32'h2A0A0C7A;//add r5,r5,r8
      #10;
      instruction18 = 32'h10800104;//addi r2,r2,4
      #10;
      instruction18 = 32'h18C00104;//addi r3,r3,4
      #10;
      instruction18 = 32'h213FFFC4;//subi r4,r4,1
      #10;
      instruction18 = 32'h20000016;//bgt r4,r0,Loop
      #10;
    end
    instruction18 = 32'h01400015;//stw r5,0(r0)
    #10;
    instruction18 = 32'h00000006;//br Stop(Stop)
    #10;
  end

  initial begin
    $dumpfile("nios2.vcd");
    $dumpvars(0,nios2_tb);
  end
endmodule

MIPS Nios2 Processor Design/nios2.vcd
$date
	Tue Oct 25 15:27:21 2016
$end

$version
	Synopsys VCS version I-2014.03-2
$end

$timescale
	10us
$end

$comment Csum: 1 8136bf8931d10109 $end


$scope module nios2_tb $end
$var wire 32 ! sum18 [31:0] $end
$var reg 32 " instruction18 [31:0] $end
$var reg 1 # clk18 $end

$scope module ft_tb $end
$var wire 1 # clk18 $end
$var wire 32 " instruction18 [31:0] $end
$var reg 32 $ out_dp18 [31:0] $end
$var reg 32 % pc18 [31:0] $end
$var reg 32 & ir18 [31:0] $end
$var reg 32 ' ALUout18 [31:0] $end
$var reg 32 ( target18 [31:0] $end
$var reg 32 ) pc18_inc [31:0] $end
$var reg 32 * memory18 [31:0] $end
$var reg 32 + pc_wb18 [31:0] $end
$var reg 5 , source_a18 [4:0] $end
$var reg 5 - source_b18 [4:0] $end
$var reg 5 . destination_18 [4:0] $end
$var reg 6 / opcode18 [5:0] $end
$var reg 32 0 r0_18 [31:0] $end
$var reg 32 1 r1_18 [31:0] $end
$var reg 32 2 r4_18 [31:0] $end
$var reg 32 3 r5_18 [31:0] $end
$var reg 32 4 four18 [31:0] $end
$var reg 32 5 one18 [31:0] $end
$var reg 32 6 pc_loop18 [31:0] $end
$var reg 32 7 N_18 [31:0] $end
$var reg 32 8 r6_18 [31:0] $end
$var reg 32 9 r7_18 [31:0] $end
$var reg 32 : r8_18 [31:0] $end
$var reg 1 ; rtype18 $end
$var reg 1 < jtype18 $end
$var reg 1 = itype18 $end
$var reg 8 > r2_addr18 [7:0] $end
$var reg 8 ? r3_addr18 [7:0] $end
$var reg 8 @ r6_addr18 [7:0] $end
$var reg 8 A r7_addr18 [7:0] $end
$var reg 8 B r8_addr18 [7:0] $end
$upscope $end

$upscope $end

$enddefinitions $end

#0
$dumpvars
0#
0=
0<
0;
bxxxxxxxxxxxxxxxxxxxxxxxxxxxxxxxx '
b00000000000000000000000000000110 7
bxxxxx .
b00000000000000000000000000000100 4
bxxxxxxxxxxxxxxxxxxxxxxxxxxxxxxxx "
b00000000000000000000000000000000 &
bxxxxxxxxxxxxxxxxxxxxxxxxxxxxxxxx *
b00000000000000000000000000000001 5
bxxxxxx /
b00000000000000000000000000000000 $
b00000000000000000000000000000000 %
b00000000000000000000000000000100 )
b00000000000000000000000000001000 6
bxxxxxxxxxxxxxxxxxxxxxxxxxxxxxxxx +
b00000000000000000000000000000000 0
bxxxxxxxxxxxxxxxxxxxxxxxxxxxxxxxx 1
b00000000 >
b00000000 ?
b00000000000000000000000000000001 2
bxxxxxxxxxxxxxxxxxxxxxxxxxxxxxxxx 3
bxxxxxxxxxxxxxxxxxxxxxxxxxxxxxxxx 8
b00000000 @
bxxxxxxxxxxxxxxxxxxxxxxxxxxxxxxxx 9
b00000000 A
bxxxxxxxxxxxxxxxxxxxxxxxxxxxxxxxx :
b00000000 B
bxxxxx ,
bxxxxx -
bzzzzzzzzzzzzzzzzzzzzzzzzzzzzzzzz !
bxxxxxxxxxxxxxxxxxxxxxxxxxxxxxxxx (
$end
#500
1#
b00100001000000000000000000010111 "
b00100001000000000000000000010111 &
b00000000000000000000000000000100 %
b00000000000000000000000000000100 +
b010111 /
b00100 ,
b00100 -
b00100 .
1=
b00000000000000000000000000000110 '
b00000000000000000000000000000110 *
b00000000000000000000000000000110 2
#1000
0#
#1500
b00000000000010100000110001111010 "
1#
b00000000000010100000110001111010 &
b00000000000000000000000000001000 %
b00000000000000000000000000001000 +
b111010 /
1;
b00000 ,
b00000 -
b00101 .
b00000000000000000000000000000000 '
b00000000000000000000000000000000 *
b00000000000000000000000000000000 3
#2000
0#
#2500
b00011000000000000000000101110011 "
1#
b00011000000000000000000101110011 &
b00000000000000000000000000001100 %
b00000000000000000000000000001100 +
b110011 /
b00011 ,
b00011 .
b00000000000000000000000000000101 '
b00000000000000000000000000000101 *
b00000000000000000000000000000101 8
#3000
0#
#3500
b00011001110000000000000000010111 "
1#
b00011001110000000000000000010111 &
b00000000000000000000000000010000 %
b00000000000000000000000000010000 +
b010111 /
b00111 -
b00000000000000000000000000000010 '
b00000000000000000000000000000010 *
b00000000000000000000000000000010 9
#4000
0#
#4500
b00110001110100000000100111111010 "
1#
b00110001110100000000100111111010 &
b00000000000000000000000000010100 %
b00000000000000000000000000010100 +
b111010 /
b00110 ,
b01000 .
b00000000000000000000000000001010 '
b00000000000000000000000000001010 *
b00000000000000000000000000001010 :
#5000
0#
#5500
b00101010000010100000110001111010 "
1#
b00101010000010100000110001111010 &
b00000000000000000000000000011000 %
b00000000000000000000000000011000 +
b00101 ,
b01000 -
b00101 .
b00000000000000000000000000001010 3
#6000
0#
#6500
b00010000100000000000000100000100 "
1#
b00010000100000000000000100000100 &
b00000000000000000000000000011100 %
b00000000000000000000000000011100 +
b000100 /
b00010 ,
b00010 -
b00010 .
b00000000000000000000000000000100 '
b00000000000000000000000000000100 *
b00000100 >
#7000
0#
#7500
b00011000110000000000000100000100 "
1#
b00011000110000000000000100000100 &
b00000000000000000000000000100000 %
b00000000000000000000000000100000 +
b00011 ,
b00011 -
b00011 .
b00000100 ?
#8000
0#
#8500
b00100001001111111111111111000100 "
1#
b00100001001111111111111111000100 &
b00000000000000000000000000100100 %
b00000000000000000000000000100100 +
b00100 ,
b00100 -
b00100 .
b00000000000000000000000000000101 '
b00000000000000000000000000000101 *
b00000000000000000000000000000101 2
#9000
0#
#9500
b00100000000000000000000000010110 "
1#
b00100000000000000000000000010110 &
b00000000000000000000000000001000 %
b00000000000000000000000000101000 +
b010110 /
b00000 -
#10000
0#
#10500
b00011000000000000000000101110011 "
1#
b00011000000000000000000101110011 &
b00000000000000000000000000001100 %
b00000000000000000000000000001100 +
b110011 /
b00011 ,
b00011 .
b00000000000000000000000000000011 '
b00000000000000000000000000000011 *
b00000000000000000000000000000011 8
#11000
0#
#11500
b00011001110000000000000000010111 "
1#
b00011001110000000000000000010111 &
b00000000000000000000000000010000 %
b00000000000000000000000000010000 +
b010111 /
b00111 -
b00000000000000000000000000001110 '
b00000000000000000000000000001110 *
b00000000000000000000000000001110 9
#12000
0#
#12500
b00110001110100000000100111111010 "
1#
b00110001110100000000100111111010 &
b00000000000000000000000000010100 %
b00000000000000000000000000010100 +
b111010 /
b00110 ,
b01000 .
b00000000000000000000000000101010 '
b00000000000000000000000000101010 *
b00000000000000000000000000101010 :
#13000
0#
#13500
b00101010000010100000110001111010 "
1#
b00101010000010100000110001111010 &
b00000000000000000000000000011000 %
b00000000000000000000000000011000 +
b00101 ,
b01000 -
b00101 .
b00000000000000000000000000110100 '
b00000000000000000000000000110100 *
b00000000000000000000000000110100 3
#14000
0#
#14500
b00010000100000000000000100000100 "
1#
b00010000100000000000000100000100 &
b00000000000000000000000000011100 %
b00000000000000000000000000011100 +
b000100 /
b00010 ,
b00010 -
b00010 .
b00000000000000000000000000001000 '
b00000000000000000000000000001000 *
b00001000 >
#15000
0#
#15500
b00011000110000000000000100000100 "
1#
b00011000110000000000000100000100 &
b00000000000000000000000000100000 %
b00000000000000000000000000100000 +
b00011 ,
b00011 -
b00011 .
b00001000 ?
#16000
0#
#16500
b00100001001111111111111111000100 "
1#
b00100001001111111111111111000100 &
b00000000000000000000000000100100 %
b00000000000000000000000000100100 +
b00100 ,
b00100 -
b00100 .
b00000000000000000000000000000100 '
b00000000000000000000000000000100 *
b00000000000000000000000000000100 2
#17000
0#
#17500
b00100000000000000000000000010110 "
1#
b00100000000000000000000000010110 &
b00000000000000000000000000001000 %
b00000000000000000000000000101000 +
b010110 /
b00000 -
#18000
0#
#18500
b00011000000000000000000101110011 "
1#
b00011000000000000000000101110011 &
b00000000000000000000000000001100 %
b00000000000000000000000000001100 +
b110011 /
b00011 ,
b00011 .
b11111111111111111111111111111010 '
b11111111111111111111111111111010 *
b11111111111111111111111111111010 8
#19000
0#
#19500
b00011001110000000000000000010111 "
1#
b00011001110000000000000000010111 &
b00000000000000000000000000010000 %
b00000000000000000000000000010000 +
b010111 /
b00111 -
b11111111111111111111111111111101 '
b11111111111111111111111111111101 *
b11111111111111111111111111111101 9
#20000
0#
#20500
b00110001110100000000100111111010 "
1#
b00110001110100000000100111111010 &
b00000000000000000000000000010100 %
b00000000000000000000000000010100 +
b111010 /
b00110 ,
b01000 .
b00000000000000000000000000010010 '
b00000000000000000000000000010010 *
b00000000000000000000000000010010 :
#21000
0#
#21500
b00101010000010100000110001111010 "
1#
b00101010000010100000110001111010 &
b00000000000000000000000000011000 %
b00000000000000000000000000011000 +
b00101 ,
b01000 -
b00101 .
b00000000000000000000000001000110 '
b00000000000000000000000001000110 *
b00000000000000000000000001000110 3
#22000
0#
#22500
b00010000100000000000000100000100 "
1#
b00010000100000000000000100000100 &
b00000000000000000000000000011100 %
b00000000000000000000000000011100 +
b000100 /
b00010 ,
b00010 -
b00010 .
b00000000000000000000000000001100 '
b00000000000000000000000000001100 *
b00001100 >
#23000
0#
#23500
b00011000110000000000000100000100 "
1#
b00011000110000000000000100000100 &
b00000000000000000000000000100000 %
b00000000000000000000000000100000 +
b00011 ,
b00011 -
b00011 .
b00001100 ?
#24000
0#
#24500
b00100001001111111111111111000100 "
1#
b00100001001111111111111111000100 &
b00000000000000000000000000100100 %
b00000000000000000000000000100100 +
b00100 ,
b00100 -
b00100 .
b00000000000000000000000000000011 '
b00000000000000000000000000000011 *
b00000000000000000000000000000011 2
#25000
0#
#25500
b00100000000000000000000000010110 "
b00100000000000000000000000010110 &
b00000000000000000000000000001000 %
b00000000000000000000000000101000 +
b010110 /
b00000 -
#26500
b00011000000000000000000101110011 "
b00011000000000000000000101110011 &
b00000000000000000000000000001100 %
b00000000000000000000000000001100 +
b110011 /
b00011 ,
b00011 .
b00000000000000000000000000010011 '
b00000000000000000000000000010011 *
b00000000000000000000000000010011 8
#27500
b00011001110000000000000000010111 "
b00011001110000000000000000010111 &
b00000000000000000000000000010000 %
b00000000000000000000000000010000 +
b010111 /
b00111 -
b00000000000000000000000000000010 '
b00000000000000000000000000000010 *
b00000000000000000000000000000010 9
#28500
b00110001110100000000100111111010 "
b00110001110100000000100111111010 &
b00000000000000000000000000010100 %
b00000000000000000000000000010100 +
b111010 /
b00110 ,
b01000 .
b00000000000000000000000000100110 '
b00000000000000000000000000100110 *
b00000000000000000000000000100110 :
#29500
b00101010000010100000110001111010 "
b00101010000010100000110001111010 &
b00000000000000000000000000011000 %
b00000000000000000000000000011000 +
b00101 ,
b01000 -
b00101 .
b00000000000000000000000001101100 '
b00000000000000000000000001101100 *
b00000000000000000000000001101100 3
#30500
b00010000100000000000000100000100 "
b00010000100000000000000100000100 &
b00000000000000000000000000011100 %
b00000000000000000000000000011100 +
b000100 /
b00010 ,
b00010 -
b00010 .
b00000000000000000000000000010000 '
b00000000000000000000000000010000 *
b00010000 >
#31500
b00011000110000000000000100000100 "
b00011000110000000000000100000100 &
b00000000000000000000000000100000 %
b00000000000000000000000000100000 +
b00011 ,
b00011 -
b00011 .
b00010000 ?
#32500
b00100001001111111111111111000100 "
b00100001001111111111111111000100 &
b00000000000000000000000000100100 %
b00000000000000000000000000100100 +
b00100 ,
b00100 -
b00100 .
b00000000000000000000000000000010 '
b00000000000000000000000000000010 *
b00000000000000000000000000000010 2
#33500
b00100000000000000000000000010110 "
b00100000000000000000000000010110 &
b00000000000000000000000000001000 %
b00000000000000000000000000101000 +
b010110 /
b00000 -
#34500
b00011000000000000000000101110011 "
b00011000000000000000000101110011 &
b00000000000000000000000000001100 %
b00000000000000000000000000001100 +
b110011 /
b00011 ,
b00011 .
b00000000000000000000000000001000 '
b00000000000000000000000000001000 *
b00000000000000000000000000001000 8
#35500
b00011001110000000000000000010111 "
b00011001110000000000000000010111 &
b00000000000000000000000000010000 %
b00000000000000000000000000010000 +
b010111 /
b00111 -
b11111111111111111111111111111011 '
b11111111111111111111111111111011 *
b11111111111111111111111111111011 9
#36500
b00110001110100000000100111111010 "
b00110001110100000000100111111010 &
b00000000000000000000000000010100 %
b00000000000000000000000000010100 +
b111010 /
b00110 ,
b01000 .
b11111111111111111111111111011000 '
b11111111111111111111111111011000 *
b11111111111111111111111111011000 :
#37500
b00101010000010100000110001111010 "
b00101010000010100000110001111010 &
b00000000000000000000000000011000 %
b00000000000000000000000000011000 +
b00101 ,
b01000 -
b00101 .
b00000000000000000000000001000100 '
b00000000000000000000000001000100 *
b00000000000000000000000001000100 3
#38500
b00010000100000000000000100000100 "
b00010000100000000000000100000100 &
b00000000000000000000000000011100 %
b00000000000000000000000000011100 +
b000100 /
b00010 ,
b00010 -
b00010 .
b00000000000000000000000000010100 '
b00000000000000000000000000010100 *
b00010100 >
#39500
b00011000110000000000000100000100 "
b00011000110000000000000100000100 &
b00000000000000000000000000100000 %
b00000000000000000000000000100000 +
b00011 ,
b00011 -
b00011 .
b00010100 ?
#40500
b00100001001111111111111111000100 "
b00100001001111111111111111000100 &
b00000000000000000000000000100100 %
b00000000000000000000000000100100 +
b00100 ,
b00100 -
b00100 .
b00000000000000000000000000000001 '
b00000000000000000000000000000001 *
b00000000000000000000000000000001 2
#41500
b00100000000000000000000000010110 "
b00100000000000000000000000010110 &
b00000000000000000000000000001000 %
b00000000000000000000000000101000 +
b010110 /
b00000 -
#42500
b00011000000000000000000101110011 "
b00011000000000000000000101110011 &
b00000000000000000000000000001100 %
b00000000000000000000000000001100 +
b110011 /
b00011 ,
b00011 .
b00000000000000000000000000001100 '
b00000000000000000000000000001100 *
b00000000000000000000000000001100 8
#43500
b00011001110000000000000000010111 "
b00011001110000000000000000010111 &
b00000000000000000000000000010000 %
b00000000000000000000000000010000 +
b010111 /
b00111 -
b00000000000000000000000000100100 '
b00000000000000000000000000100100 *
b00000000000000000000000000100100 9
#44500
b00110001110100000000100111111010 "
b00110001110100000000100111111010 &
b00000000000000000000000000010100 %
b00000000000000000000000000010100 +
b111010 /
b00110 ,
b01000 .
b00000000000000000000000110110000 '
b00000000000000000000000110110000 *
b00000000000000000000000110110000 :
#45500
b00101010000010100000110001111010 "
b00101010000010100000110001111010 &
b00000000000000000000000000011000 %
b00000000000000000000000000011000 +
b00101 ,
b01000 -
b00101 .
b00000000000000000000000111110100 '
b00000000000000000000000111110100 *
b00000000000000000000000111110100 3
#46500
b00010000100000000000000100000100 "
b00010000100000000000000100000100 &
b00000000000000000000000000011100 %
b00000000000000000000000000011100 +
b000100 /
b00010 ,
b00010 -
b00010 .
b00000000000000000000000000011000 '
b00000000000000000000000000011000 *
b00011000 >
#47500
b00011000110000000000000100000100 "
b00011000110000000000000100000100 &
b00000000000000000000000000100000 %
b00000000000000000000000000100000 +
b00011 ,
b00011 -
b00011 .
b00011000 ?
#48500
b00100001001111111111111111000100 "
b00100001001111111111111111000100 &
b00000000000000000000000000100100 %
b00000000000000000000000000100100 +
b00100 ,
b00100 -
b00100 .
b00000000000000000000000000000000 '
b00000000000000000000000000000000 *
b00000000000000000000000000000000 2
#49500
b00100000000000000000000000010110 "
b00100000000000000000000000010110 &
b00000000000000000000000000101000 %
b00000000000000000000000000101000 +
b010110 /
b00000 -
#50500
b00000001010000000000000000010101 "
b00000001010000000000000000010101 &
b00000000000000000000000000101100 %
b00000000000000000000000000101100 +
b010101 /
b00000 ,
b00101 -
b00000 .
b00000000000000000000001000001001 '
b00000000000000000000001000001001 *
b00000000000000000000001000001001 3
#51500
b00000000000000000000000000000110 "
b00000000000000000000000000000110 &
b00000000000000000000000000110000 %
b00000000000000000000000000110000 +
b000110 /
b00000 -
